shell_scripter/__init__.py
shell_scripter-0.0.1.dist-info/LICENSE
shell_scripter-0.0.1.dist-info/METADATA
shell_scripter-0.0.1.dist-info/WHEEL
shell_scripter-0.0.1.dist-info/top_level.txt
shell_scripter-0.0.1.dist-info/RECORD
