Metadata-Version: 2.1
Name: shell-scripter
Version: 0.0.1
Summary: A shell scripting library for Python
Home-page: https://github.com/ZacJW/shell-scripter
Author: Zac Wilson
Author-email: zac@zacjw.com
License: UNKNOWN
Project-URL: Bug Tracker, https://github.com/ZacJW/shell-scripter/issues
Platform: UNKNOWN
Classifier: Programming Language :: Python :: 3
Classifier: License :: OSI Approved :: MIT License
Requires-Python: >=3.6
License-File: LICENSE
